{
  "variables": {
    "cpu_cores": "1",
    "memory": "2048",
    "disk_size": "10000",
    "headless": "true",
    "iso_url": "http://releases.ubuntu.com/14.04.4/ubuntu-14.04.4-server-amd64.iso",
    "iso_checksum": "07e4bb5569814eab41fafac882ba127893e3ff0bdb7ec931c9b2d040e3e94e7a",
    "iso_checksum_type": "sha256",
    "ssh_username": "vagrant",
    "ssh_password": "vagrant"
  },
  "builders": [
  {
  "name": "libvirt",
  "vm_name": "ubuntu-1404-libvirt",
  "type": "qemu",
  "format": "qcow2",
  "disk_interface": "virtio",
  "accelerator": "kvm",
  "qemuargs": [["-m", "{{user `memory`}}M"],
               ["-smp", "{{user `cpu_cores`}}"],
               ["-machine", "type=pc,accel=kvm"],
               ["-device", "virtio-net-pci,netdev=user.0"]],
  "disk_size": "{{user `disk_size`}}",
  "iso_url": "{{user `iso_url`}}",
  "headless": "{{user `headless`}}",
  "iso_checksum": "{{user `iso_checksum`}}",
  "iso_checksum_type": "{{user `iso_checksum_type`}}",
  "ssh_username": "{{user `ssh_username`}}",
  "ssh_password": "{{user `ssh_password`}}",
  "ssh_wait_timeout": "60m",
  "http_directory" : "preseed",
  "boot_command" : [
            "<esc><esc><enter><wait>",
            "/install/vmlinuz noapic ",
            "preseed/url=http://{{ .HTTPIP }}:{{ .HTTPPort }}/preseed_libvirt.cfg ",
            "debian-installer=en_US auto locale=en_US kbd-chooser/method=us ",
            "hostname=ubuntu ",
            "fb=false debconf/frontend=noninteractive ",
            "keyboard-configuration/modelcode=SKIP keyboard-configuration/layout=USA ",
            "keyboard-configuration/variant=USA console-setup/ask_detect=false ",
            "initrd=/install/initrd.gz -- <enter>"
        ],  
  "shutdown_command": "echo 'vagrant' | sudo -S shutdown -P now"
  }
 ],
  "provisioners": [
  {
    "execute_command": "echo 'vagrant' | {{.Vars}} sudo -E -S bash '{{.Path}}'",
    "type": "shell",
    "script": "scripts/vagrant.sh"
  },
  {
    "execute_command": "echo 'vagrant' | {{.Vars}} sudo -E -S bash '{{.Path}}'",
    "type": "shell",
    "script": "scripts/install-docker.sh"
  },
  {
    "execute_command": "echo 'vagrant' | {{.Vars}} sudo -E -S bash '{{.Path}}'",
    "type": "shell",
    "script": "scripts/net-next.sh"
  },
  {
    "execute_command": "echo 'vagrant' | {{.Vars}} sudo -E -S bash '{{.Path}}'",
    "type": "shell",
    "script": "scripts/go.sh"
  },
  {
    "execute_command": "echo 'vagrant' | {{ .Vars }} sudo -E -S bash '{{ .Path }}'",
    "type": "shell",
    "script": "scripts/cleanup.sh"
  }
 ],
  "post-processors": [
  [{
      "type": "vagrant",
      "compression_level": 9,
      "keep_input_artifact": true,
      "output": "ubuntu-1404-{{.BuildName}}.box"
  },
  {
      "type": "atlas",
      "only": ["libvirt"],
      "artifact": "noironetworks/net-next",
      "artifact_type": "vagrant.box",
      "metadata": {
          "provider": "libvirt",
	  "version": "0.0.32",
	  "description": "Snapshot of net-next kernel"
      }
  }]
 ]
}
