{
  "name": "Cilium",
  "image": "quay.io/cilium/cilium-builder:910d82b880e36b1ec1a50bdf764fc60152afdb0b@sha256:863ce967282b9f7e132238f53421b719ce9589d8ee0bbcf265b3981beb190f6a",
  "workspaceFolder": "/go/src/github.com/cilium/cilium",
  "workspaceMount": "source=${localWorkspaceFolder},target=/go/src/github.com/cilium/cilium,type=bind",
  "features": {
    "ghcr.io/devcontainers/features/docker-in-docker": {}
  },
  "mounts": [
    // To enable kernel modules for devcontainer
    "source=/lib/modules,target=/lib/modules,type=bind,readonly",
    "source=/usr/lib/modules,target=/usr/lib/modules,type=bind,readonly"
  ],
  "runArgs": [
    "--sysctl", "net.ipv6.conf.all.disable_ipv6=0"
  ],
  "postCreateCommand": "git config --global --add safe.directory /go/src/github.com/cilium/cilium"
}
